hangmangame_46165/__init__.py
hangmangame_46165/hangman.py
hangmangame_46165-0.1.dist-info/METADATA
hangmangame_46165-0.1.dist-info/WHEEL
hangmangame_46165-0.1.dist-info/top_level.txt
hangmangame_46165-0.1.dist-info/RECORD
