Metadata-Version: 2.1
Name: hangmangame-46165
Version: 0.1
Summary: This is the Hangman Game Package
Author: Shahzad Ahmed Khan
License: UNKNOWN
Platform: UNKNOWN
